
{
  "header": {
    "reportVersion": 2,
    "event": "Allocation failed - JavaScript heap out of memory",
    "trigger": "FatalError",
    "filename": "report.20201228.153156.17012.0.001.json",
    "dumpEventTime": "2020-12-28T15:31:56Z",
    "dumpEventTimeStamp": "1609180316897",
    "processId": 17012,
    "threadId": null,
    "cwd": "C:\\Users\\Igor Gimenez\\Desktop\\Proyectos ANGULAR\\Financorp\\service-web",
    "commandLine": [
      "D:\\Programas\\nodeJs\\node.exe",
      "C:\\Users\\Igor Gimenez\\AppData\\Roaming\\npm/node_modules/@angular/cli/bin/ng",
      "build",
      "--prod"
    ],
    "nodejsVersion": "v12.16.3",
    "wordSize": 64,
    "arch": "x64",
    "platform": "win32",
    "componentVersions": {
      "node": "12.16.3",
      "v8": "7.8.279.23-node.35",
      "uv": "1.34.2",
      "zlib": "1.2.11",
      "brotli": "1.0.7",
      "ares": "1.16.0",
      "modules": "72",
      "nghttp2": "1.40.0",
      "napi": "5",
      "llhttp": "2.0.4",
      "http_parser": "2.9.3",
      "openssl": "1.1.1g",
      "cldr": "36.0",
      "icu": "65.1",
      "tz": "2019c",
      "unicode": "12.1"
    },
    "release": {
      "name": "node",
      "lts": "Erbium",
      "headersUrl": "https://nodejs.org/download/release/v12.16.3/node-v12.16.3-headers.tar.gz",
      "sourceUrl": "https://nodejs.org/download/release/v12.16.3/node-v12.16.3.tar.gz",
      "libUrl": "https://nodejs.org/download/release/v12.16.3/win-x64/node.lib"
    },
    "osName": "Windows_NT",
    "osRelease": "10.0.19041",
    "osVersion": "Windows 10 Home",
    "osMachine": "x86_64",
    "cpus": [
      {
        "model": "Intel(R) Core(TM) i7-7700HQ CPU @ 2.80GHz",
        "speed": 2808,
        "user": 5278171,
        "nice": 0,
        "sys": 5087687,
        "idle": 36233187,
        "irq": 1210906
      },
      {
        "model": "Intel(R) Core(TM) i7-7700HQ CPU @ 2.80GHz",
        "speed": 2808,
        "user": 1871515,
        "nice": 0,
        "sys": 1620703,
        "idle": 43106687,
        "irq": 692734
      },
      {
        "model": "Intel(R) Core(TM) i7-7700HQ CPU @ 2.80GHz",
        "speed": 2808,
        "user": 4854921,
        "nice": 0,
        "sys": 1716500,
        "idle": 40027484,
        "irq": 56265
      },
      {
        "model": "Intel(R) Core(TM) i7-7700HQ CPU @ 2.80GHz",
        "speed": 2808,
        "user": 2150281,
        "nice": 0,
        "sys": 982906,
        "idle": 43465718,
        "irq": 20062
      },
      {
        "model": "Intel(R) Core(TM) i7-7700HQ CPU @ 2.80GHz",
        "speed": 2808,
        "user": 3883593,
        "nice": 0,
        "sys": 1480906,
        "idle": 41234406,
        "irq": 31656
      },
      {
        "model": "Intel(R) Core(TM) i7-7700HQ CPU @ 2.80GHz",
        "speed": 2808,
        "user": 2646828,
        "nice": 0,
        "sys": 990156,
        "idle": 42961921,
        "irq": 14390
      },
      {
        "model": "Intel(R) Core(TM) i7-7700HQ CPU @ 2.80GHz",
        "speed": 2808,
        "user": 5379265,
        "nice": 0,
        "sys": 1392437,
        "idle": 39827203,
        "irq": 28640
      },
      {
        "model": "Intel(R) Core(TM) i7-7700HQ CPU @ 2.80GHz",
        "speed": 2808,
        "user": 2692453,
        "nice": 0,
        "sys": 1257234,
        "idle": 42649203,
        "irq": 15234
      }
    ],
    "networkInterfaces": [
      {
        "name": "Ethernet 2",
        "internal": false,
        "mac": "54:cd:27:f2:f0:01",
        "address": "fe80::e5fa:ec5d:203d:e5dc",
        "netmask": "ffff:ffff:ffff:ffff::",
        "family": "IPv6",
        "scopeid": 17
      },
      {
        "name": "Ethernet 2",
        "internal": false,
        "mac": "54:cd:27:f2:f0:01",
        "address": "172.16.121.47",
        "netmask": "255.255.252.0",
        "family": "IPv4"
      },
      {
        "name": "Wi-Fi",
        "internal": false,
        "mac": "98:22:ef:70:41:ff",
        "address": "fe80::38a0:214f:4b66:f6ea",
        "netmask": "ffff:ffff:ffff:ffff::",
        "family": "IPv6",
        "scopeid": 11
      },
      {
        "name": "Wi-Fi",
        "internal": false,
        "mac": "98:22:ef:70:41:ff",
        "address": "192.168.100.96",
        "netmask": "255.255.255.0",
        "family": "IPv4"
      },
      {
        "name": "Loopback Pseudo-Interface 1",
        "internal": true,
        "mac": "00:00:00:00:00:00",
        "address": "::1",
        "netmask": "ffff:ffff:ffff:ffff:ffff:ffff:ffff:ffff",
        "family": "IPv6",
        "scopeid": 0
      },
      {
        "name": "Loopback Pseudo-Interface 1",
        "internal": true,
        "mac": "00:00:00:00:00:00",
        "address": "127.0.0.1",
        "netmask": "255.0.0.0",
        "family": "IPv4"
      }
    ],
    "host": "LAPTOP-7M8LNDOA"
  },
  "javascriptStack": {
    "message": "No stack.",
    "stack": [
      "Unavailable."
    ]
  },
  "nativeStack": [
    {
      "pc": "0x00007ff7317e2449",
      "symbol": "std::basic_ostream<char,std::char_traits<char> >::operator<<+11577"
    },
    {
      "pc": "0x00007ff7317e69a9",
      "symbol": "std::basic_ostream<char,std::char_traits<char> >::operator<<+29337"
    },
    {
      "pc": "0x00007ff7317e5828",
      "symbol": "std::basic_ostream<char,std::char_traits<char> >::operator<<+24856"
    },
    {
      "pc": "0x00007ff73191d8c2",
      "symbol": "v8::base::CPU::has_sse+68658"
    },
    {
      "pc": "0x00007ff732139bbe",
      "symbol": "v8::Isolate::ReportExternalAllocationLimitReached+94"
    },
    {
      "pc": "0x00007ff732121c91",
      "symbol": "v8::SharedArrayBuffer::Externalize+833"
    },
    {
      "pc": "0x00007ff731fee1ec",
      "symbol": "v8::internal::Heap::EphemeronKeyWriteBarrierFromCode+1436"
    },
    {
      "pc": "0x00007ff731ff9420",
      "symbol": "v8::internal::Heap::ProtectUnprotectedMemoryChunks+1312"
    },
    {
      "pc": "0x00007ff731ff5f44",
      "symbol": "v8::internal::Heap::PageFlagsAreConsistent+3204"
    },
    {
      "pc": "0x00007ff731feb743",
      "symbol": "v8::internal::Heap::CollectGarbage+1283"
    },
    {
      "pc": "0x00007ff731fe9db4",
      "symbol": "v8::internal::Heap::AddRetainedMap+2452"
    },
    {
      "pc": "0x00007ff73200afbd",
      "symbol": "v8::internal::Factory::NewFillerObject+61"
    },
    {
      "pc": "0x00007ff731d71871",
      "symbol": "v8::internal::interpreter::JumpTableTargetOffsets::iterator::operator=+1665"
    },
    {
      "pc": "0x00007ff732586c4d",
      "symbol": "v8::internal::SetupIsolateDelegate::SetupHeap+546637"
    },
    {
      "pc": "0x00000134e7bd2294",
      "symbol": ""
    }
  ],
  "javascriptHeap": {
    "totalMemory": 2156072960,
    "totalCommittedMemory": 2156072960,
    "usedMemory": 2120472784,
    "availableMemory": 49820328,
    "memoryLimit": 2197815296,
    "heapSpaces": {
      "read_only_space": {
        "memorySize": 262144,
        "committedMemory": 262144,
        "capacity": 32808,
        "used": 32808,
        "available": 0
      },
      "new_space": {
        "memorySize": 6291456,
        "committedMemory": 6291456,
        "capacity": 3142368,
        "used": 726536,
        "available": 2415832
      },
      "old_space": {
        "memorySize": 2059546624,
        "committedMemory": 2059546624,
        "capacity": 2055896280,
        "used": 2053376488,
        "available": 2519792
      },
      "code_space": {
        "memorySize": 4886528,
        "committedMemory": 4886528,
        "capacity": 4285408,
        "used": 4285408,
        "available": 0
      },
      "map_space": {
        "memorySize": 29626368,
        "committedMemory": 29626368,
        "capacity": 6842720,
        "used": 6842720,
        "available": 0
      },
      "large_object_space": {
        "memorySize": 54837248,
        "committedMemory": 54837248,
        "capacity": 54664536,
        "used": 54664536,
        "available": 0
      },
      "code_large_object_space": {
        "memorySize": 622592,
        "committedMemory": 622592,
        "capacity": 544288,
        "used": 544288,
        "available": 0
      },
      "new_large_object_space": {
        "memorySize": 0,
        "committedMemory": 0,
        "capacity": 3142368,
        "used": 0,
        "available": 3142368
      }
    }
  },
  "resourceUsage": {
    "userCpuSeconds": 85.828,
    "kernelCpuSeconds": 5.671,
    "cpuConsumptionPercent": 182.998,
    "maxRss": 2260099072,
    "pageFaults": {
      "IORequired": 961039,
      "IONotRequired": 0
    },
    "fsActivity": {
      "reads": 8042,
      "writes": 6
    }
  },
  "libuv": [
  ],
  "workers": [
  ],
  "environmentVariables": {
    "ALLUSERSPROFILE": "C:\\ProgramData",
    "APPDATA": "C:\\Users\\Igor Gimenez\\AppData\\Roaming",
    "BROWSERSLIST_IGNORE_OLD_DATA": "1",
    "ChocolateyInstall": "C:\\ProgramData\\chocolatey",
    "ChocolateyLastPathUpdate": "132344925233348035",
    "CHROME_CRASHPAD_PIPE_NAME": "\\\\.\\pipe\\crashpad_19076_FDFLXWVDHSQVTEMU",
    "CommonProgramFiles": "C:\\Program Files\\Common Files",
    "CommonProgramFiles(x86)": "C:\\Program Files (x86)\\Common Files",
    "CommonProgramW6432": "C:\\Program Files\\Common Files",
    "COMPUTERNAME": "LAPTOP-7M8LNDOA",
    "ComSpec": "C:\\WINDOWS\\system32\\cmd.exe",
    "DriverData": "C:\\Windows\\System32\\Drivers\\DriverData",
    "HOMEDRIVE": "C:",
    "HOMEPATH": "\\Users\\Igor Gimenez",
    "JAVA_HOME": "C:\\Program Files\\Java\\jdk1.8.0_181",
    "LOCALAPPDATA": "C:\\Users\\Igor Gimenez\\AppData\\Local",
    "LOGONSERVER": "\\\\LAPTOP-7M8LNDOA",
    "M2_HOME": "C:\\Program Files\\apache-maven-3.6.3",
    "NUMBER_OF_PROCESSORS": "8",
    "OneDrive": "C:\\Users\\Igor Gimenez\\OneDrive",
    "OneDriveConsumer": "C:\\Users\\Igor Gimenez\\OneDrive",
    "ORIGINAL_XDG_CURRENT_DESKTOP": "undefined",
    "OS": "Windows_NT",
    "Path": "C:\\Python38\\Scripts\\;C:\\Python38\\;C:\\Program Files (x86)\\Common Files\\Oracle\\Java\\javapath;C:\\Program Files (x86)\\Intel\\iCLS Client\\;C:\\Program Files\\Intel\\iCLS Client\\;C:\\Windows\\system32;C:\\Windows;C:\\Windows\\System32\\Wbem;C:\\Windows\\System32\\WindowsPowerShell\\v1.0\\;C:\\Program Files (x86)\\Intel\\Intel(R) Management Engine Components\\DAL;C:\\Program Files\\Intel\\Intel(R) Management Engine Components\\DAL;C:\\Program Files (x86)\\Intel\\Intel(R) Management Engine Components\\IPT;C:\\Program Files\\Intel\\Intel(R) Management Engine Components\\IPT;C:\\Program Files (x86)\\NVIDIA Corporation\\PhysX\\Common;C:\\Program Files\\Java\\jdk1.8.0_181\\bin;C:\\WINDOWS\\system32;C:\\WINDOWS;C:\\WINDOWS\\System32\\Wbem;C:\\WINDOWS\\System32\\WindowsPowerShell\\v1.0\\;C:\\WINDOWS\\System32\\OpenSSH\\;C:\\Program Files\\Microsoft SQL Server\\Client SDK\\ODBC\\110\\Tools\\Binn\\;C:\\Program Files (x86)\\Microsoft SQL Server\\120\\Tools\\Binn\\;C:\\Program Files\\Microsoft SQL Server\\120\\Tools\\Binn\\;C:\\Program Files\\Microsoft SQL Server\\120\\DTS\\Binn\\;C:\\Program Files (x86)\\Microsoft SQL Server\\120\\Tools\\Binn\\ManagementStudio\\;C:\\Program Files (x86)\\Microsoft SQL Server\\120\\DTS\\Binn\\;C:\\Program Files (x86)\\Microsoft SQL Server\\Client SDK\\ODBC\\130\\Tools\\Binn\\;C:\\Program Files (x86)\\Microsoft SQL Server\\130\\Tools\\Binn\\;C:\\Program Files (x86)\\Microsoft SQL Server\\130\\DTS\\Binn\\;C:\\Program Files (x86)\\Microsoft SQL Server\\130\\Tools\\Binn\\ManagementStudio\\;C:\\Program Files\\dotnet\\;C:\\Program Files\\Microsoft SQL Server\\130\\Tools\\Binn\\;C:\\Program Files\\PuTTY\\;D:\\Programas\\nodeJs\\;C:\\ProgramData\\chocolatey\\bin;C:\\Program Files (x86)\\Microsoft SQL Server\\150\\DTS\\Binn\\;C:\\Program Files\\Git\\cmd;C:\\Program Files\\NVIDIA Corporation\\NVIDIA NvDLISR;C:\\Program Files\\Java\\jdk1.8.0_181\\bin;;C:\\WINDOWS\\system32;C:\\WINDOWS;C:\\WINDOWS\\System32\\Wbem;C:\\WINDOWS\\System32\\WindowsPowerShell\\v1.0\\;C:\\WINDOWS\\System32\\OpenSSH\\;C:\\Program Files\\Microsoft SQL Server\\Client SDK\\ODBC\\170\\Tools\\Binn\\;C:\\Users\\Igor Gimenez\\AppData\\Local\\Microsoft\\WindowsApps;D:\\Programas\\Microsoft VS Code\\bin;C:\\Program Files\\apache-maven-3.6.3\\bin;C:\\Users\\Igor Gimenez\\AppData\\Roaming\\npm;C:\\Windows\\Microsoft.NET\\Framework64\\v3.5;C:\\Users\\Igor Gimenez\\.dotnet\\tools",
    "PATHEXT": ".COM;.EXE;.BAT;.CMD;.VBS;.VBE;.JS;.JSE;.WSF;.WSH;.MSC;.PY;.PYW;.CPL",
    "PROCESSOR_ARCHITECTURE": "AMD64",
    "PROCESSOR_IDENTIFIER": "Intel64 Family 6 Model 158 Stepping 9, GenuineIntel",
    "PROCESSOR_LEVEL": "6",
    "PROCESSOR_REVISION": "9e09",
    "ProgramData": "C:\\ProgramData",
    "ProgramFiles": "C:\\Program Files",
    "ProgramFiles(x86)": "C:\\Program Files (x86)",
    "ProgramW6432": "C:\\Program Files",
    "PSModulePath": "C:\\Users\\Igor Gimenez\\Documents\\WindowsPowerShell\\Modules;C:\\Program Files\\WindowsPowerShell\\Modules;C:\\WINDOWS\\system32\\WindowsPowerShell\\v1.0\\Modules;C:\\Program Files (x86)\\Microsoft SQL Server\\120\\Tools\\PowerShell\\Modules\\;C:\\Program Files (x86)\\Microsoft SQL Server\\130\\Tools\\PowerShell\\Modules\\",
    "PUBLIC": "C:\\Users\\Public",
    "SESSIONNAME": "Console",
    "SystemDrive": "C:",
    "SystemRoot": "C:\\WINDOWS",
    "TEMP": "C:\\Users\\IGORGI~1\\AppData\\Local\\Temp",
    "TMP": "C:\\Users\\IGORGI~1\\AppData\\Local\\Temp",
    "USERDOMAIN": "LAPTOP-7M8LNDOA",
    "USERDOMAIN_ROAMINGPROFILE": "LAPTOP-7M8LNDOA",
    "USERNAME": "Igor Gimenez",
    "USERPROFILE": "C:\\Users\\Igor Gimenez",
    "windir": "C:\\WINDOWS",
    "TERM_PROGRAM": "vscode",
    "TERM_PROGRAM_VERSION": "1.52.1",
    "LANG": "en_US.UTF-8",
    "COLORTERM": "truecolor",
    "VSCODE_GIT_IPC_HANDLE": "\\\\.\\pipe\\vscode-git-85a6e1152c-sock",
    "GIT_ASKPASS": "d:\\Programas\\Microsoft VS Code\\resources\\app\\extensions\\git\\dist\\askpass.sh",
    "VSCODE_GIT_ASKPASS_NODE": "D:\\Programas\\Microsoft VS Code\\Code.exe",
    "VSCODE_GIT_ASKPASS_MAIN": "d:\\Programas\\Microsoft VS Code\\resources\\app\\extensions\\git\\dist\\askpass-main.js"
  },
  "sharedObjects": [
    "D:\\Programas\\nodeJs\\node.exe",
    "C:\\WINDOWS\\SYSTEM32\\ntdll.dll",
    "C:\\WINDOWS\\System32\\KERNEL32.DLL",
    "C:\\WINDOWS\\System32\\KERNELBASE.dll",
    "C:\\WINDOWS\\System32\\WS2_32.dll",
    "C:\\WINDOWS\\System32\\RPCRT4.dll",
    "C:\\WINDOWS\\SYSTEM32\\dbghelp.dll",
    "C:\\WINDOWS\\System32\\PSAPI.DLL",
    "C:\\WINDOWS\\System32\\ucrtbase.dll",
    "C:\\WINDOWS\\System32\\ADVAPI32.dll",
    "C:\\WINDOWS\\System32\\msvcrt.dll",
    "C:\\WINDOWS\\SYSTEM32\\IPHLPAPI.DLL",
    "C:\\WINDOWS\\SYSTEM32\\USERENV.dll",
    "C:\\WINDOWS\\System32\\sechost.dll",
    "C:\\WINDOWS\\System32\\USER32.dll",
    "C:\\WINDOWS\\System32\\win32u.dll",
    "C:\\WINDOWS\\System32\\GDI32.dll",
    "C:\\WINDOWS\\System32\\gdi32full.dll",
    "C:\\WINDOWS\\System32\\msvcp_win.dll",
    "C:\\WINDOWS\\System32\\CRYPT32.dll",
    "C:\\WINDOWS\\System32\\bcrypt.dll",
    "C:\\WINDOWS\\SYSTEM32\\WINMM.dll",
    "C:\\WINDOWS\\System32\\IMM32.DLL",
    "C:\\WINDOWS\\SYSTEM32\\powrprof.dll",
    "C:\\WINDOWS\\SYSTEM32\\UMPDC.dll",
    "C:\\WINDOWS\\SYSTEM32\\CRYPTBASE.DLL",
    "C:\\WINDOWS\\system32\\uxtheme.dll",
    "C:\\WINDOWS\\System32\\combase.dll",
    "C:\\WINDOWS\\system32\\mswsock.dll",
    "C:\\WINDOWS\\SYSTEM32\\kernel.appcore.dll",
    "C:\\WINDOWS\\System32\\bcryptprimitives.dll",
    "\\\\?\\C:\\Users\\Igor Gimenez\\Desktop\\Proyectos ANGULAR\\Financorp\\service-web\\node_modules\\node-sass\\vendor\\win32-x64-72\\binding.node",
    "C:\\WINDOWS\\System32\\NSI.dll",
    "C:\\WINDOWS\\SYSTEM32\\dhcpcsvc6.DLL",
    "C:\\WINDOWS\\SYSTEM32\\dhcpcsvc.DLL",
    "C:\\WINDOWS\\SYSTEM32\\DNSAPI.dll",
    "C:\\WINDOWS\\system32\\napinsp.dll",
    "C:\\WINDOWS\\system32\\pnrpnsp.dll",
    "C:\\WINDOWS\\system32\\wshbth.dll",
    "C:\\WINDOWS\\system32\\NLAapi.dll",
    "C:\\WINDOWS\\System32\\winrnr.dll"
  ]
}